vibesort_mcp/__init__.py
vibesort_mcp/__main__.py
vibesort_mcp/server.py
vibesort_mcp-0.1.1.dist-info/licenses/LICENSE
vibesort_mcp-0.1.1.dist-info/METADATA
vibesort_mcp-0.1.1.dist-info/WHEEL
vibesort_mcp-0.1.1.dist-info/entry_points.txt
vibesort_mcp-0.1.1.dist-info/top_level.txt
vibesort_mcp-0.1.1.dist-info/RECORD
