Metadata-Version: 2.4
Name: vibesort-mcp
Version: 0.1.1
Summary: A O(1) sorting method MCP leveraging the Vibesort Algorithm
Keywords: ai,llm,agents,mcp,sorting,vibesort
Classifier: Programming Language :: Python :: 3
Classifier: License :: OSI Approved :: MIT License
Classifier: Operating System :: OS Independent
Requires-Python: >=3.12
License-File: LICENSE
Requires-Dist: openai>=1.0
Requires-Dist: pydantic>=2.0.0
Requires-Dist: fastmcp
Dynamic: license-file
